setup.py
brynq_sdk_allsolutions/__init__.py
brynq_sdk_allsolutions.egg-info/PKG-INFO
brynq_sdk_allsolutions.egg-info/SOURCES.txt
brynq_sdk_allsolutions.egg-info/dependency_links.txt
brynq_sdk_allsolutions.egg-info/not-zip-safe
brynq_sdk_allsolutions.egg-info/requires.txt
brynq_sdk_allsolutions.egg-info/top_level.txt