Metadata-Version: 1.0
Name: brynq-sdk-allsolutions
Version: 2.0.1
Summary: All solutions wrapper from BrynQ
Home-page: UNKNOWN
Author: BrynQ
Author-email: support@brynq.com
License: BrynQ License
Platform: UNKNOWN
